[{"point":[11,0,0]},{"point":[10,0,0]},{"point":[9,0,0]},{"point":[8,0,0]},{"point":[7,0,0]},{"point":[6,0,0]},{"point":[5,0,0]},{"point":[4,0,0]},{"point":[3,0,0]},{"point":[2,0,0]},{"point":[1,0,0]},{"point":[0,0,0]},{"point":[0,0,1]},{"point":[1,0,1]},{"point":[2,0,1]},{"point":[3,0,1]},{"point":[4,0,1]},{"point":[5,0,1]},{"point":[6,0,1]},{"point":[7,0,1]},{"point":[8,0,1]},{"point":[9,0,1]},{"point":[10,0,1]},{"point":[11,0,1]},{"point":[11,0,2]},{"point":[10,0,2]},{"point":[9,0,2]},{"point":[8,0,2]},{"point":[7,0,2]},{"point":[6,0,2]},{"point":[5,0,2]},{"point":[4,0,2]},{"point":[3,0,2]},{"point":[2,0,2]},{"point":[1,0,2]},{"point":[0,0,2]},{"point":[0,0,3]},{"point":[1,0,3]},{"point":[2,0,3]},{"point":[3,0,3]},{"point":[4,0,3]},{"point":[5,0,3]},{"point":[6,0,3]},{"point":[7,0,3]},{"point":[8,0,3]},{"point":[9,0,3]},{"point":[10,0,3]},{"point":[11,0,3]},{"point":[11,0,4]},{"point":[10,0,4]},{"point":[9,0,4]},{"point":[8,0,4]},{"point":[7,0,4]},{"point":[6,0,4]},{"point":[5,0,4]},{"point":[4,0,4]},{"point":[3,0,4]},{"point":[2,0,4]},{"point":[1,0,4]},{"point":[0,0,4]},{"point":[0,0,5]},{"point":[1,0,5]},{"point":[2,0,5]},{"point":[3,0,5]},{"point":[4,0,5]},{"point":[5,0,5]},{"point":[6,0,5]},{"point":[7,0,5]},{"point":[8,0,5]},{"point":[9,0,5]},{"point":[10,0,5]},{"point":[11,0,5]},{"point":[11,0,6]},{"point":[10,0,6]},{"point":[9,0,6]},{"point":[8,0,6]},{"point":[7,0,6]},{"point":[6,0,6]},{"point":[5,0,6]},{"point":[4,0,6]},{"point":[3,0,6]},{"point":[2,0,6]},{"point":[1,0,6]},{"point":[0,0,6]},{"point":[0,0,7]},{"point":[1,0,7]},{"point":[2,0,7]},{"point":[3,0,7]},{"point":[4,0,7]},{"point":[5,0,7]},{"point":[6,0,7]},{"point":[7,0,7]},{"point":[8,0,7]},{"point":[9,0,7]},{"point":[10,0,7]},{"point":[11,0,7]},{"point":[11,0,8]},{"point":[10,0,8]},{"point":[9,0,8]},{"point":[8,0,8]},{"point":[7,0,8]},{"point":[6,0,8]},{"point":[5,0,8]},{"point":[4,0,8]},{"point":[3,0,8]},{"point":[2,0,8]},{"point":[1,0,8]},{"point":[0,0,8]},{"point":[0,0,9]},{"point":[1,0,9]},{"point":[2,0,9]},{"point":[3,0,9]},{"point":[4,0,9]},{"point":[5,0,9]},{"point":[6,0,9]},{"point":[7,0,9]},{"point":[8,0,9]},{"point":[9,0,9]},{"point":[10,0,9]},{"point":[11,0,9]}]
